onyx_otc/__init__.py
onyx_otc/cli/__init__.py
onyx_otc/cli/app.py
onyx_otc/cli/common.py
onyx_otc/cli/stream.py
onyx_otc/common.py
onyx_otc/py.typed
onyx_otc/requests.py
onyx_otc/responses.py
onyx_otc/timestamp.py
onyx_otc/types.py
onyx_otc/utils.py
onyx_otc/v2/__init__.py
onyx_otc/v2/common_pb2.py
onyx_otc/v2/common_pb2.pyi
onyx_otc/v2/common_pb2_grpc.pyi
onyx_otc/v2/requests_pb2.py
onyx_otc/v2/requests_pb2.pyi
onyx_otc/v2/requests_pb2_grpc.pyi
onyx_otc/v2/responses_pb2.py
onyx_otc/v2/responses_pb2.pyi
onyx_otc/v2/responses_pb2_grpc.pyi
onyx_otc/v2/types_pb2.py
onyx_otc/v2/types_pb2.pyi
onyx_otc/v2/types_pb2_grpc.pyi
onyx_otc/websocket_v2.py
onyx_otc-0.3.1.dist-info/LICENSE
onyx_otc-0.3.1.dist-info/METADATA
onyx_otc-0.3.1.dist-info/WHEEL
onyx_otc-0.3.1.dist-info/entry_points.txt
onyx_otc-0.3.1.dist-info/RECORD
