Metadata-Version: 2.3
Name: onyx-otc
Version: 0.3.1
Summary: Onyx otc python client and documentation
Author: lsbardel
Author-email: lsbardella@onyxcapitaltechnology.com
Requires-Python: >=3.11,<4.0
Classifier: Programming Language :: Python :: 3
Classifier: Programming Language :: Python :: 3.11
Classifier: Programming Language :: Python :: 3.12
Classifier: Programming Language :: Python :: 3.13
Provides-Extra: cli
Requires-Dist: aiohttp (>=3.10.10,<4.0.0)
Requires-Dist: click (>=8.1.8,<9.0.0) ; extra == "cli"
Requires-Dist: grpcio (>=1.64.1,<2.0.0)
Requires-Dist: protobuf (>=5.27.2,<6.0.0)
Requires-Dist: pydantic (>=2.10.6,<3.0.0)
Requires-Dist: python-dotenv (>=1.0.1,<2.0.0)
Project-URL: Homepage, https://github.com/Onyx-Capital-Technology/onyx-otc
Project-URL: Repository, https://github.com/Onyx-Capital-Technology/onyx-otc
